astrowisp-1.5.0-cp38-cp38-win_amd64.whl
astrowisp/__init__.py
astrowisp/__main__.py
astrowisp/_initialize_library.py
astrowisp/background.py
astrowisp/fistar.exe
astrowisp/fit_star_shape.py
astrowisp/grcollect.exe
astrowisp/hat_masks.py
astrowisp/io_tree.py
astrowisp/libastrowisp.dll
astrowisp/libastrowisp.dll.a
astrowisp/piecewise_bicubic_psf.py
astrowisp/piecewise_bicubic_psf_map.py
astrowisp/psf_base.py
astrowisp/subpixphot.py
astrowisp/fake_image/__init__.py
astrowisp/fake_image/bipolynomial_psf_piece.py
astrowisp/fake_image/image.py
astrowisp/fake_image/piecewise_bicubic_psf.py
astrowisp/fake_image/piecewise_psf.py
astrowisp/fake_image/psf_piece.py
astrowisp/tests/__init__.py
astrowisp/tests/test_background.py
astrowisp/tests/test_fake_image.py
astrowisp/tests/test_fistar.py
astrowisp/tests/test_piecewise_bicubic_psf.py
astrowisp/tests/utilities.py
astrowisp/tests/test_data/XO1_test_img.fistar
astrowisp/tests/test_data/XO1_test_img.fits
astrowisp/tests/test_data/XO1_test_img_applechip.fistar
astrowisp/tests/test_fit_star_shape/__init__.py
astrowisp/tests/test_fit_star_shape/noiseless_tests.py
astrowisp/tests/test_fit_star_shape/utils.py
astrowisp/utils/__init__.py
astrowisp/utils/explore_prf.py
astrowisp/utils/file_utilities.py
astrowisp.libs/.load-order-astrowisp-1.5.0
astrowisp.libs/libgcc_s_seh-1-1db15e20215e4b4e9242de60fbd7aa3e.dll
astrowisp.libs/libstdc++-6-0183f4a6ed32cf2f13fa2c5afcb89543.dll
astrowisp.libs/libwinpthread-1-4548f7146d9ae327aa190a90256f0e98.dll
astrowisp-1.5.0.dist-info/DELVEWHEEL
astrowisp-1.5.0.dist-info/LICENSE
astrowisp-1.5.0.dist-info/METADATA
astrowisp-1.5.0.dist-info/WHEEL
astrowisp-1.5.0.dist-info/RECORD
