Metadata-Version: 2.1
Name: astrowisp
Version: 1.5.0
Summary: Tools for extracting photometry from wide-field night sky images
Author-Email: Kaloyan Penev <Kaloyan.Penev@utdallas.edu>, Angel Romero <Angel.Romero@utdallas.edu>, Ashkan Jafarzadeh <ashkan.jafarzadeh@utdallas.edu>, Istvan Domsa <istvan.domsa@gmail.com>
Maintainer-Email: Kaloyan Penev <Kaloyan.Penev@utdallas.edu>, Angel Romero <Angel.Romero@utdallas.edu>, Ashkan Jafarzadeh <ashkan.jafarzadeh@utdallas.edu>
License:                     GNU GENERAL PUBLIC LICENSE
Classifier: Development Status :: 4 - Beta
Classifier: Environment :: Console
Classifier: Operating System :: Microsoft :: Windows
Classifier: Operating System :: MacOS
Classifier: Operating System :: POSIX :: Linux
Classifier: Intended Audience :: Developers
Classifier: Intended Audience :: Science/Research
Classifier: License :: OSI Approved :: MIT License
Classifier: Programming Language :: C++
Classifier: Programming Language :: C
Classifier: Programming Language :: Python :: 3
Classifier: Topic :: Scientific/Engineering :: Image Processing
Classifier: Topic :: Scientific/Engineering :: Astronomy
Classifier: Topic :: Scientific/Engineering :: Physics
Project-URL: source, https://github.com/kpenev/AstroWISP
Project-URL: documentation, https://kpenev.github.io/AstroWISP/
Requires-Python: >=3.7
Requires-Dist: numpy<2
Requires-Dist: scipy
Requires-Dist: astropy
Provides-Extra: test
Requires-Dist: asteval; extra == "test"
Requires-Dist: pandas; extra == "test"
Provides-Extra: visualize
Requires-Dist: configargparse; extra == "visualize"
Requires-Dist: matplotlib; extra == "visualize"
Requires-Dist: xalglib; extra == "visualize"
